openFileDialogue/__init__.py
openFileDialogue/openFileDialogue.py
openfiledialogue-0.0.4.dist-info/METADATA
openfiledialogue-0.0.4.dist-info/WHEEL
openfiledialogue-0.0.4.dist-info/licenses/LICENSE
openfiledialogue-0.0.4.dist-info/RECORD
