Metadata-Version: 2.1
Name: openFileDialogue
Version: 0.0.4
Summary: A simple file explorer made using tkinter
Author-email: James Caroe <jamescaroe@gmail.com>
License-File: LICENSE
Classifier: License :: OSI Approved :: MIT License
Classifier: Operating System :: Microsoft :: Windows
Classifier: Operating System :: POSIX :: Linux
Classifier: Programming Language :: Python :: 3
Requires-Python: >=3.7
